multi_agent/server.py
single_agent/server.py
iflow_mcp_contextualai_contextual_mcp_server-0.1.0.dist-info/METADATA
iflow_mcp_contextualai_contextual_mcp_server-0.1.0.dist-info/WHEEL
iflow_mcp_contextualai_contextual_mcp_server-0.1.0.dist-info/entry_points.txt
iflow_mcp_contextualai_contextual_mcp_server-0.1.0.dist-info/top_level.txt
iflow_mcp_contextualai_contextual_mcp_server-0.1.0.dist-info/RECORD
