Metadata-Version: 2.4
Name: iflow-mcp_contextualai_contextual-mcp-server
Version: 0.1.0
Summary: A Model Context Protocol (MCP) server that provides RAG capabilities using Contextual AI
Requires-Python: >=3.10
Requires-Dist: contextual-client>=0.5.1
Requires-Dist: httpx>=0.28.1
Requires-Dist: mcp[cli]>=1.6.0
Requires-Dist: dotenv
Requires-Dist: uv
Requires-Dist: tiktoken
